
{    
    {
        "action": "authenticate",
        "key": "lkjf9032jsdh823", 
        "return": "SUCCESS"
    },
    {   
        "action": "get",
        "class": "Human",
        "id": 0,
        "name": "Peter",
        "age": 42, 
        "city": "Sävsjö"
    },
    {
        "action": "get",
        "class": "Human",
        "id": 1,
        "name": "Olof", 
        "city": "Nässjö"
    },
    {
        "action": "createHtmlDiv",
        "div_text": "Hello World!",
        "return": "<div>Hello World!</div>"
    },
    {
        "action": "someVoidFunction",
        "return": "SUCCESS"
    }
}
